README.md
setup.py
PermCCA.egg-info/PKG-INFO
PermCCA.egg-info/SOURCES.txt
PermCCA.egg-info/dependency_links.txt
PermCCA.egg-info/requires.txt
PermCCA.egg-info/top_level.txt
permcca/__init__.py
permcca/inference.py
permcca/interpret.py
permcca/models.py
permcca/permute.py
permcca/plotting.py
permcca/preproc.py
test/test.py