Metadata-Version: 2.1
Name: PermCCA
Version: 0.1.3
Summary: A permutation-based CCA analysis toolbox
Home-page: https://github.com/Wetiqe/PermCCA
Author: Neil Jianzhang Ni
Author-email: jzni132134@gmail.com
Classifier: Development Status :: 1 - Planning
Classifier: Programming Language :: Python :: 3
Classifier: Programming Language :: Python :: 3.6
Classifier: Programming Language :: Python :: 3.7
Classifier: Programming Language :: Python :: 3.8
Classifier: Programming Language :: Python :: 3.9
Classifier: Programming Language :: Python :: 3.10
